aiotelegram.py
aiotelegram-0.2.0.dist-info/DESCRIPTION.rst
aiotelegram-0.2.0.dist-info/METADATA
aiotelegram-0.2.0.dist-info/RECORD
aiotelegram-0.2.0.dist-info/WHEEL
aiotelegram-0.2.0.dist-info/metadata.json
aiotelegram-0.2.0.dist-info/top_level.txt
