Metadata-Version: 2.0
Name: aiotelegram
Version: 0.2.0
Summary: Tiny asyncio-based telgram api wrapper library
Home-page: https://github.com/pohmelie/aiotelegram
Author: pohmelie
Author-email: multisosnooley@gmail.com
License: WTFPL
Platform: UNKNOWN
Classifier: Development Status :: 5 - Production/Stable
Classifier: Programming Language :: Python
Classifier: Programming Language :: Python :: 3
Classifier: Programming Language :: Python :: 3.5
Requires-Dist: aiohttp
